[{"indicator": "max_high_temp", "historic": {"minimum": 90.9938, "maximum": 108.80415, "min_model_avg": 96.05326386666664, "max_model_avg": 100.17363556666666, "average": 95.33422919900437}, "future": {"minimum": 94.05966, "maximum": 121.35594, "min_model_avg": 100.7801244, "max_model_avg": 112.7837733, "average": 102.00152097177197}}, {"indicator": "dry_spells", "historic": {"minimum": 4.418472, "maximum": 19.81737, "min_model_avg": 10.246254026666666, "max_model_avg": 12.61746776666666, "average": 10.93131132817569}, "future": {"minimum": 3.5033457, "maximum": 20.329483, "min_model_avg": 9.447673816666669, "max_model_avg": 15.743221233333333, "average": 11.670954638219325}}, {"indicator": "changed_seasonal_patterns"}]