[{"indicator": "max_high_temp", "historic": {"minimum": 92.91396, "maximum": 109.624466, "min_model_avg": 98.96968663333335, "max_model_avg": 102.74801656666668, "average": 98.00961612317136}, "future": {"minimum": 96.18598, "maximum": 123.650536, "min_model_avg": 103.73689013333335, "max_model_avg": 114.6136712, "average": 104.46132026344364}}, {"indicator": "dry_spells", "historic": {"minimum": 6.721035, "maximum": 22.201576, "min_model_avg": 12.949359233333332, "max_model_avg": 15.2045281, "average": 13.60969709838281}, "future": {"minimum": 8.3150425, "maximum": 24.57286, "min_model_avg": 12.987462883333336, "max_model_avg": 18.836065533333336, "average": 14.453430757435731}}, {"indicator": "changed_seasonal_patterns"}]