[{"indicator": "max_high_temp", "historic": {"minimum": 92.912224, "maximum": 101.13748, "min_model_avg": 95.91716266666667, "max_model_avg": 97.52753823333333, "average": 93.63783871090826}, "future": {"minimum": 96.465546, "maximum": 109.443184, "min_model_avg": 98.86706693333332, "max_model_avg": 104.5904605, "average": 98.11204614640687}}, {"indicator": "dry_spells", "historic": {"minimum": 5.3709183, "maximum": 19.926872, "min_model_avg": 11.876785126666665, "max_model_avg": 13.822612666666666, "average": 12.561258179655358}, "future": {"minimum": 6.1095877, "maximum": 20.40548, "min_model_avg": 11.123853293333333, "max_model_avg": 14.392077533333337, "average": 12.508677508247656}}, {"indicator": "changed_seasonal_patterns"}]