[{"indicator": "changed_seasonal_patterns"}, {"indicator": "max_high_temp", "historic": {"minimum": 86.80179, "maximum": 102.84293, "min_model_avg": 93.17922343333333, "max_model_avg": 96.45133849999999, "average": 92.14507129489238}, "future": {"minimum": 92.37011, "maximum": 117.45001, "min_model_avg": 98.22463359999996, "max_model_avg": 108.46283260000001, "average": 99.09528226978769}}, {"indicator": "extreme_precip_events", "historic": {"minimum": 0, "maximum": 1.9090835, "min_model_avg": 0.095317079417, "max_model_avg": 0.28151208296666663, "average": 0.18261980193684899}, "future": {"minimum": 0, "maximum": 4.965249, "min_model_avg": 0.16757285911033337, "max_model_avg": 0.7937402857666667, "average": 0.4161350536604961}}, {"indicator": "dry_spells", "historic": {"minimum": 2.594075, "maximum": 18.716097, "min_model_avg": 8.578406410000001, "max_model_avg": 11.086865583333331, "average": 9.478548210916959}, "future": {"minimum": 4.580944, "maximum": 19.536146, "min_model_avg": 9.255027116666666, "max_model_avg": 14.162433033333333, "average": 10.522947363692708}}]