[{"indicator": "changed_seasonal_patterns"}, {"indicator": "max_high_temp", "historic": {"minimum": 86.54763, "maximum": 104.55605, "min_model_avg": 92.88031436666667, "max_model_avg": 96.75844286666667, "average": 92.15992913367}, "future": {"minimum": 93.1733, "maximum": 118.687386, "min_model_avg": 98.47123733333335, "max_model_avg": 108.17484803333333, "average": 99.13676316758585}}, {"indicator": "extreme_precip_events", "historic": {"minimum": 0, "maximum": 3.377231, "min_model_avg": 0.1162699681, "max_model_avg": 0.43167897617999995, "average": 0.24768753958037812}, "future": {"minimum": 0, "maximum": 4.409491, "min_model_avg": 0.19525203209, "max_model_avg": 0.8553725326366666, "average": 0.4607303903447729}}, {"indicator": "dry_spells"}]