[{"indicator": "changed_seasonal_patterns"}, {"indicator": "max_high_temp", "historic": {"minimum": 88.02929, "maximum": 106.36071, "min_model_avg": 94.22347383333334, "max_model_avg": 97.2620345, "average": 93.18499880421207}, "future": {"minimum": 92.20092, "maximum": 117.6918, "min_model_avg": 99.6600936, "max_model_avg": 108.38524406666669, "average": 100.17673057004127}}, {"indicator": "extreme_precip_events", "historic": {"minimum": 0, "maximum": 2.4977932, "min_model_avg": 0.15317389996666667, "max_model_avg": 0.40109745678333353, "average": 0.2749119194332539}, "future": {"minimum": 0, "maximum": 4.195388, "min_model_avg": 0.2261867880333334, "max_model_avg": 0.7763018884666667, "average": 0.41666239997586063}}, {"indicator": "dry_spells"}]