[{"indicator": "changed_seasonal_patterns"}, {"indicator": "max_high_temp", "historic": {"minimum": 85.76435, "maximum": 101.328804, "min_model_avg": 92.08177046666667, "max_model_avg": 95.48760150000003, "average": 91.11350422033217}, "future": {"minimum": 90.69925, "maximum": 116.19568, "min_model_avg": 97.21451653333334, "max_model_avg": 107.74483316666668, "average": 97.90840525714053}}, {"indicator": "extreme_precip_events", "historic": {"minimum": 0, "maximum": 2.9996974, "min_model_avg": 0.09854414713333333, "max_model_avg": 0.35178829139999995, "average": 0.20435538911880333}, "future": {"minimum": 0, "maximum": 4.136608, "min_model_avg": 0.11072918333333333, "max_model_avg": 0.8350171708666666, "average": 0.39121750719035364}}, {"indicator": "dry_spells", "historic": {"minimum": 2.8325076, "maximum": 18.90167, "min_model_avg": 8.750536403333335, "max_model_avg": 10.79160793333333, "average": 9.649541016486062}, "future": {"minimum": 4.8850694, "maximum": 18.948462, "min_model_avg": 9.326935353333333, "max_model_avg": 13.97006663333333, "average": 10.571448316095001}}]