[{"indicator": "dry_spells"}, {"indicator": "extreme_precip_events", "historic": {"minimum": 0, "maximum": 3.9679508, "min_model_avg": 0.44142400160000006, "max_model_avg": 0.8336685387666666, "average": 0.6003949149744824}, "future": {"minimum": 0, "maximum": 5.0479383, "min_model_avg": 0.4257044290626667, "max_model_avg": 1.1725534258333334, "average": 0.7368480315787365}}, {"indicator": "max_high_temp", "historic": {"minimum": 91.86865, "maximum": 114.592285, "min_model_avg": 100.7568519, "max_model_avg": 105.3687525, "average": 100.43636797440645}, "future": {"minimum": 97.50192, "maximum": 127.49372, "min_model_avg": 105.23579506666667, "max_model_avg": 114.68733503333331, "average": 106.64724682324358}}]