[{"indicator": "dry_spells"}, {"indicator": "extreme_precip_events", "historic": {"minimum": 0, "maximum": 0.7414288, "min_model_avg": 0.01861676535, "max_model_avg": 0.07744864325666664, "average": 0.040456085425386805}, "future": {"minimum": 0, "maximum": 1.4973236, "min_model_avg": 0.02917457654, "max_model_avg": 0.1334640410233333, "average": 0.060284638777394185}}, {"indicator": "max_high_temp", "historic": {"minimum": 93.868744, "maximum": 111.03432, "min_model_avg": 102.30885893333334, "max_model_avg": 104.53573223333335, "average": 100.19980005723896}, "future": {"minimum": 98.9704, "maximum": 121.655556, "min_model_avg": 106.06276553333332, "max_model_avg": 113.49946843333333, "average": 107.04171419993355}}]