[{"indicator": "dry_spells"}, {"indicator": "extreme_precip_events", "historic": {"minimum": 0, "maximum": 3.4557528, "min_model_avg": 0.41066649366666674, "max_model_avg": 0.8200798182033334, "average": 0.5766213510595286}, "future": {"minimum": 0, "maximum": 6.035903, "min_model_avg": 0.32220213763000005, "max_model_avg": 1.1285869350200002, "average": 0.78697406741637}}, {"indicator": "max_high_temp", "historic": {"minimum": 91.72444, "maximum": 113.46388, "min_model_avg": 100.82819453333333, "max_model_avg": 105.29801920000001, "average": 100.18289718930397}, "future": {"minimum": 97.58767, "maximum": 123.62537, "min_model_avg": 105.64513796666667, "max_model_avg": 113.53254166666669, "average": 106.33175828969824}}]