[{"indicator": "sea_level_rise"}, {"indicator": "dry_spells"}, {"indicator": "extreme_precip_events", "historic": {"minimum": 0, "maximum": 3.1920438, "min_model_avg": 0.15867807582333335, "max_model_avg": 0.37910217948, "average": 0.2738528512404445}, "future": {"minimum": 0, "maximum": 5.3633265, "min_model_avg": 0.11781957874666668, "max_model_avg": 0.6586679947033335, "average": 0.4026024229327301}}, {"indicator": "max_high_temp", "historic": {"minimum": 91.96135, "maximum": 112.126045, "min_model_avg": 101.27940766666667, "max_model_avg": 104.56661759999999, "average": 99.84434661837156}, "future": {"minimum": 97.5899, "maximum": 122.074455, "min_model_avg": 105.94159833333332, "max_model_avg": 114.38937993333334, "average": 106.66856901692614}}, {"indicator": "saltwater_intrusion"}]