[{"indicator": "max_high_temp", "historic": {"minimum": 87.99618, "maximum": 104.47699, "min_model_avg": 93.60142603333333, "max_model_avg": 97.41819086666669, "average": 92.80090866691656}, "future": {"minimum": 92.50355, "maximum": 118.999664, "min_model_avg": 97.67807496666666, "max_model_avg": 110.18579833333334, "average": 99.6336389693448}}, {"indicator": "dry_spells", "historic": {"minimum": 2.9066422, "maximum": 18.363049, "min_model_avg": 8.226816426666666, "max_model_avg": 10.342301126666666, "average": 9.079131376442698}, "future": {"minimum": 2.9124632, "maximum": 19.292421, "min_model_avg": 8.862871169999998, "max_model_avg": 13.627049133333335, "average": 10.234821443318967}}, {"indicator": "changed_seasonal_patterns"}]