[{"indicator": "max_high_temp", "historic": {"minimum": 88.36123, "maximum": 105.00798, "min_model_avg": 92.80877326666669, "max_model_avg": 96.9718057, "average": 92.39298217371146}, "future": {"minimum": 90.95412, "maximum": 115.84616, "min_model_avg": 97.105511, "max_model_avg": 110.06639643333332, "average": 99.06445214837709}}, {"indicator": "dry_spells", "historic": {"minimum": 3.234416, "maximum": 19.078478, "min_model_avg": 9.177311430000001, "max_model_avg": 11.689444433333335, "average": 9.970221659139343}, "future": {"minimum": 4.068059, "maximum": 20.297842, "min_model_avg": 9.52486995, "max_model_avg": 14.180833433333333, "average": 11.010600175281908}}, {"indicator": "changed_seasonal_patterns"}]