[{"indicator": "max_high_temp", "historic": {"minimum": 89.40914, "maximum": 107.47989, "min_model_avg": 95.15810203333334, "max_model_avg": 99.38472653333335, "average": 94.64466147849822}, "future": {"minimum": 94.19658, "maximum": 119.72656, "min_model_avg": 100.92014776666664, "max_model_avg": 111.62973793333332, "average": 101.89389191500615}}, {"indicator": "dry_spells", "historic": {"minimum": 3.7413437, "maximum": 20.3638, "min_model_avg": 9.130835053333332, "max_model_avg": 12.315433533333334, "average": 10.535106935558835}, "future": {"minimum": 4.5678473, "maximum": 19.490967, "min_model_avg": 9.996663189999998, "max_model_avg": 15.041529333333331, "average": 11.463757376809042}}, {"indicator": "changed_seasonal_patterns"}]