[{"indicator": "changed_seasonal_patterns"}, {"indicator": "max_high_temp", "historic": {"minimum": 86.64608, "maximum": 104.2828, "min_model_avg": 93.41430819999998, "max_model_avg": 97.08762130000004, "average": 92.48823277218584}, "future": {"minimum": 90.465385, "maximum": 116.666885, "min_model_avg": 97.38525933333332, "max_model_avg": 108.163348, "average": 99.45336694909739}}, {"indicator": "extreme_precip_events", "historic": {"minimum": 0, "maximum": 2.1057901, "min_model_avg": 0.058659744386666664, "max_model_avg": 0.24438234256666666, "average": 0.14896915308728131}, "future": {"minimum": 0, "maximum": 2.7185228, "min_model_avg": 0.028155537067666672, "max_model_avg": 0.3908285265333334, "average": 0.219463390026896}}, {"indicator": "dry_spells", "historic": {"minimum": 9.409723, "maximum": 23.986284, "min_model_avg": 14.266984016666667, "max_model_avg": 16.578621599999998, "average": 15.101291655665312}, "future": {"minimum": 8.739791, "maximum": 23.850807, "min_model_avg": 12.99844783333333, "max_model_avg": 17.711917149999998, "average": 15.274309962786717}}]