[{"indicator": "dry_spells", "historic": {"minimum": 11.552816, "maximum": 24.161697, "min_model_avg": 17.539582733333337, "max_model_avg": 19.067316866666665, "average": 17.568426049770938}, "future": {"minimum": 11.60377, "maximum": 27.497166, "min_model_avg": 16.425722566666668, "max_model_avg": 19.971852166666668, "average": 17.76619628786672}}, {"indicator": "extreme_precip_events", "historic": {"minimum": 0, "maximum": 1.1580826, "min_model_avg": 0.009679213133333335, "max_model_avg": 0.07451516521666667, "average": 0.03958627826230044}, "future": {"minimum": 0, "maximum": 2.0245278, "min_model_avg": 0.00811598729, "max_model_avg": 0.2508588599666666, "average": 0.06570536060748156}}, {"indicator": "changed_seasonal_patterns"}, {"indicator": "max_high_temp", "historic": {"minimum": 86.72791, "maximum": 107.41149, "min_model_avg": 96.88129746666665, "max_model_avg": 100.63883186666668, "average": 96.2446852788604}, "future": {"minimum": 91.80602, "maximum": 120.12721, "min_model_avg": 99.3415757, "max_model_avg": 109.28838716666668, "average": 102.39137861510824}}]