[{"indicator": "max_high_temp", "historic": {"minimum": 84.76857, "maximum": 97.62417, "min_model_avg": 88.29273349999997, "max_model_avg": 91.34078456666666, "average": 87.3765575480555}, "future": {"minimum": 88.59442, "maximum": 110.505844, "min_model_avg": 92.12028603333333, "max_model_avg": 102.56261566666669, "average": 93.49784114220708}}, {"indicator": "dry_spells", "historic": {"minimum": 3.548286, "maximum": 17.433687, "min_model_avg": 9.540309666666667, "max_model_avg": 11.084255493333336, "average": 9.855844607700833}, "future": {"minimum": 4.383888, "maximum": 18.81378, "min_model_avg": 8.191953216666665, "max_model_avg": 13.847857749999998, "average": 10.486748110474885}}, {"indicator": "changed_seasonal_patterns"}]