[{"indicator": "dry_spells"}, {"indicator": "extreme_precip_events", "historic": {"minimum": 0, "maximum": 5.63155, "min_model_avg": 0.5695405105333333, "max_model_avg": 1.0461978979333333, "average": 0.7613846678318863}, "future": {"minimum": 0, "maximum": 7.6674347, "min_model_avg": 0.6309368290999999, "max_model_avg": 1.6105417913000002, "average": 0.9868239686382676}}, {"indicator": "max_high_temp", "historic": {"minimum": 93.26579, "maximum": 113.25799, "min_model_avg": 101.68809169999999, "max_model_avg": 105.52967679999998, "average": 100.91079172908873}, "future": {"minimum": 97.62302, "maximum": 123.790924, "min_model_avg": 105.01142756666667, "max_model_avg": 114.61349076666666, "average": 106.90818234531258}}]