[{"indicator": "dry_spells"}, {"indicator": "extreme_precip_events", "historic": {"minimum": 0, "maximum": 3.9448524, "min_model_avg": 0.4195994858666666, "max_model_avg": 0.7931486728066667, "average": 0.5954021440200614}, "future": {"minimum": 0, "maximum": 7.133056, "min_model_avg": 0.6320802377499999, "max_model_avg": 1.4492174195333334, "average": 0.8510956550617044}}, {"indicator": "max_high_temp", "historic": {"minimum": 92.71563, "maximum": 112.09531, "min_model_avg": 100.98372396666667, "max_model_avg": 104.64729453333332, "average": 100.20477114860539}, "future": {"minimum": 95.62316, "maximum": 122.68773, "min_model_avg": 104.51135863333333, "max_model_avg": 113.81486546666665, "average": 106.0669375117055}}]