[{"indicator": "max_consecutive_dry_days"}, {"indicator": "max_high_temp", "historic": {"minimum": 81.7556, "maximum": 100.5094, "min_model_avg": 90.8292625, "max_model_avg": 93.71496576666667, "average": 90.09225264983387}, "future": {"minimum": 89.28964, "maximum": 113.31439, "min_model_avg": 95.70578403333336, "max_model_avg": 103.62606566666663, "average": 96.35022603916657}}, {"indicator": "extreme_precip_events", "historic": {"minimum": 0.023044402, "maximum": 7.144354, "min_model_avg": 1.7080069813333334, "max_model_avg": 2.2769560749999997, "average": 1.9549498826044527}, "future": {"minimum": 0.019783158, "maximum": 8.633249, "min_model_avg": 1.6356980644666668, "max_model_avg": 3.793091219999999, "average": 2.3827770392240253}}, {"indicator": "dry_spells"}]