[{"indicator": "changed_seasonal_patterns"}, {"indicator": "extreme_precip_events", "historic": {"minimum": 0, "maximum": 1.9320724, "min_model_avg": 0.033887617105, "max_model_avg": 0.20856668886333332, "average": 0.11021159101061222}, "future": {"minimum": 0, "maximum": 2.9714708, "min_model_avg": 0.05944949811266665, "max_model_avg": 0.331433354225, "average": 0.17877353455516676}}, {"indicator": "sea_level_rise"}, {"indicator": "max_high_temp", "historic": {"minimum": 84.43132, "maximum": 98.41804, "min_model_avg": 89.37429203333335, "max_model_avg": 92.58397056666668, "average": 88.6108789480356}, "future": {"minimum": 88.207306, "maximum": 113.9376, "min_model_avg": 91.1791171, "max_model_avg": 105.4723456, "average": 95.74028750475804}}, {"indicator": "ocean_acidification"}]