[{"indicator": "max_high_temp", "historic": {"minimum": 93.15079, "maximum": 107.82211, "min_model_avg": 99.98809476666665, "max_model_avg": 102.4298912, "average": 98.1038278713475}, "future": {"minimum": 98.21775, "maximum": 121.61086, "min_model_avg": 103.45543826666668, "max_model_avg": 114.02213029999999, "average": 104.47699201385083}}, {"indicator": "dry_spells", "historic": {"minimum": 6.243732, "maximum": 20.090563, "min_model_avg": 11.822800633333332, "max_model_avg": 13.205573516666668, "average": 12.164366612877371}, "future": {"minimum": 4.1200366, "maximum": 23.021406, "min_model_avg": 10.589898736666667, "max_model_avg": 16.912030366666663, "average": 12.801385549744586}}, {"indicator": "changed_seasonal_patterns"}]