[{"indicator": "dry_spells", "historic": {"minimum": 12.353566, "maximum": 25.362633, "min_model_avg": 16.75787471666667, "max_model_avg": 18.711612666666667, "average": 17.34077571288198}, "future": {"minimum": 11.019865, "maximum": 25.284893, "min_model_avg": 15.837136816666668, "max_model_avg": 19.84340635, "average": 17.40142063489375}}, {"indicator": "extreme_precip_events", "historic": {"minimum": 0, "maximum": 1.5662111, "min_model_avg": 0.028047844666666665, "max_model_avg": 0.21549647696666668, "average": 0.08520913065762141}, "future": {"minimum": 0, "maximum": 2.685839, "min_model_avg": 0.029007890733333333, "max_model_avg": 0.30646317819999996, "average": 0.1451236038507003}}, {"indicator": "changed_seasonal_patterns"}, {"indicator": "max_high_temp", "historic": {"minimum": 88.72426, "maximum": 112.545845, "min_model_avg": 98.1540712, "max_model_avg": 102.0788574, "average": 97.24044298808884}, "future": {"minimum": 93.29101, "maximum": 122.29998, "min_model_avg": 100.9272000333333, "max_model_avg": 112.55999806666668, "average": 104.07426594120041}}]