[{"indicator": "max_high_temp", "historic": {"minimum": 90.4509, "maximum": 106.26585, "min_model_avg": 96.49090463333333, "max_model_avg": 99.42475506666668, "average": 95.34318934383823}, "future": {"minimum": 94.88148, "maximum": 118.457, "min_model_avg": 101.43014283333332, "max_model_avg": 111.84426653333331, "average": 101.8658928343575}}, {"indicator": "dry_spells", "historic": {"minimum": 4.5137825, "maximum": 21.36072, "min_model_avg": 11.275596693333334, "max_model_avg": 13.421208683333335, "average": 11.829263025937177}, "future": {"minimum": 6.3532524, "maximum": 22.238565, "min_model_avg": 10.378448429999999, "max_model_avg": 17.303504333333333, "average": 12.761220439311117}}, {"indicator": "changed_seasonal_patterns"}]