[{"indicator": "sea_level_rise"}, {"indicator": "dry_spells"}, {"indicator": "extreme_precip_events", "historic": {"minimum": 0, "maximum": 3.5293574, "min_model_avg": 0.20132370601000002, "max_model_avg": 0.5369952247099999, "average": 0.3761012074763201}, "future": {"minimum": 0, "maximum": 5.1000886, "min_model_avg": 0.27397803307866664, "max_model_avg": 0.9308298640386667, "average": 0.565864686386074}}, {"indicator": "max_high_temp", "historic": {"minimum": 93.73276, "maximum": 107.89226, "min_model_avg": 101.45662133333333, "max_model_avg": 103.44929253333333, "average": 99.34260275652096}, "future": {"minimum": 98.52606, "maximum": 116.29605, "min_model_avg": 105.2572388, "max_model_avg": 110.55170723333336, "average": 104.76982826158233}}, {"indicator": "saltwater_intrusion"}]