[{"indicator": "dry_spells"}, {"indicator": "extreme_precip_events", "historic": {"minimum": 0, "maximum": 6.9150023, "min_model_avg": 1.0932887828333335, "max_model_avg": 1.7769411283333334, "average": 1.2925524617933364}, "future": {"minimum": 0, "maximum": 8.841923, "min_model_avg": 1.1407796039999998, "max_model_avg": 2.355125098755666, "average": 1.5995878469893996}}, {"indicator": "max_high_temp", "historic": {"minimum": 93.84747, "maximum": 110.07037, "min_model_avg": 99.9678475, "max_model_avg": 102.54591756666667, "average": 98.19577765007125}, "future": {"minimum": 97.97224, "maximum": 119.42907, "min_model_avg": 102.71950519999999, "max_model_avg": 110.46624480000001, "average": 103.66115625941627}}]