[{"indicator": "max_high_temp", "historic": {"minimum": 89.50704, "maximum": 103.063934, "min_model_avg": 94.04441833333337, "max_model_avg": 97.05581716666669, "average": 93.11596570769561}, "future": {"minimum": 93.46912, "maximum": 119.96793, "min_model_avg": 99.44284813333334, "max_model_avg": 111.1183266, "average": 100.71821975144854}}, {"indicator": "dry_spells", "historic": {"minimum": 4.0010524, "maximum": 19.55158, "min_model_avg": 9.989166653333333, "max_model_avg": 12.256151016666669, "average": 10.969375234005177}, "future": {"minimum": 4.419399, "maximum": 20.099417, "min_model_avg": 10.418044286666667, "max_model_avg": 14.13648588333333, "average": 11.62388094961503}}, {"indicator": "changed_seasonal_patterns"}]