[{"indicator": "max_high_temp", "historic": {"minimum": 92.74686, "maximum": 105.63727, "min_model_avg": 97.5392778, "max_model_avg": 99.69246393333333, "average": 95.90230726433231}, "future": {"minimum": 96.75521, "maximum": 115.49736, "min_model_avg": 101.19058806666666, "max_model_avg": 109.77796766666668, "average": 102.02269715804603}}, {"indicator": "dry_spells", "historic": {"minimum": 3.470441, "maximum": 21.349054, "min_model_avg": 10.072798893333335, "max_model_avg": 11.886910473333337, "average": 10.870682587547366}, "future": {"minimum": 4.4860964, "maximum": 21.552961, "min_model_avg": 10.175108669999998, "max_model_avg": 14.937122533333332, "average": 11.80222907901797}}, {"indicator": "changed_seasonal_patterns"}]