[{"indicator": "dry_spells"}, {"indicator": "extreme_precip_events", "historic": {"minimum": 0, "maximum": 1.0388949, "min_model_avg": 0.08722770865333332, "max_model_avg": 0.19259120466666663, "average": 0.12291189533753633}, "future": {"minimum": 0, "maximum": 1.4729844, "min_model_avg": 0.11311760368, "max_model_avg": 0.3034633867, "average": 0.1902175671869819}}, {"indicator": "changed_seasonal_patterns"}, {"indicator": "max_high_temp", "historic": {"minimum": 77.23211, "maximum": 90.930664, "min_model_avg": 83.55834983333334, "max_model_avg": 85.67364923333335, "average": 82.06906958132564}, "future": {"minimum": 83.32152, "maximum": 102.81056, "min_model_avg": 88.53138603333332, "max_model_avg": 96.67439176666667, "average": 89.04183530923824}}]